{
    "Trima": [
        {
            "No": "1",
            "Client": "Baia Mare",
            "Serial": "1T01036",
            "Hours": "14655",
            "Runs": "5623",
            "Soft": "6.0.6",
            "Setup": "19.09.2019",
            "PM": "12.2022",
            "Year": "2001",
            "Tech": "Ciobanu"
        },
        {
            "No": "2",
            "Client": "Focsani",
            "Serial": "1T01225",
            "Hours": "1607",
            "Runs": "475",
            "Soft": "6.0.6",
            "Setup": "10.09.2019",
            "PM": "11.2022",
            "Year": "2002",
            "Tech": "Cristea"
        },
        {
            "No": "3",
            "Client": "Buzau 1",
            "Serial": "1T01608",
            "Hours": "32915",
            "Runs": "6628",
            "Soft": "6.0.6",
            "Setup": "10.09.2020",
            "PM": "11.2022",
            "Year": "2003",
            "Tech": "Cristea"
        },
        {
            "No": "4",
            "Client": "Bistrita",
            "Serial": "1T01612",
            "Hours": "36391",
            "Runs": "7618",
            "Soft": "6.0.6",
            "Setup": "19.09.2019",
            "PM": "12.2022",
            "Year": "2003",
            "Tech": "Ciobanu"
        },
        {
            "No": "5",
            "Client": "Constanta",
            "Serial": "1T03180",
            "Hours": "9646",
            "Runs": "2426",
            "Soft": "6.0.8",
            "Setup": "21.01.2021",
            "PM": "11.2022",
            "Year": "2006",
            "Tech": "Cristea"
        },
        {
            "No": "6",
            "Client": "Satu Mare 2",
            "Serial": "1T03605",
            "Hours": "8745",
            "Runs": "3635",
            "Soft": "6.0.6",
            "Setup": "13.04.2021",
            "PM": "12.2022",
            "Year": "2007",
            "Tech": "Ciobanu"
        },
        {
            "No": "7",
            "Client": "Cluj 2",
            "Serial": "1T04818",
            "Hours": "6632",
            "Runs": "1889",
            "Soft": "6.0.9",
            "Setup": "13.11.2020",
            "PM": "12.2022",
            "Year": "2010",
            "Tech": "Ciobanu"
        },
        {
            "No": "8",
            "Client": "Slobozia",
            "Serial": "1T04820",
            "Hours": "7322",
            "Runs": "2212",
            "Soft": "6.0.9",
            "Setup": "20.01.2021",
            "PM": "12.2022",
            "Year": "2010",
            "Tech": "Cristea"
        },
        {
            "No": "9",
            "Client": "Depozit 1",
            "Serial": "1T04899",
            "Hours": "2558",
            "Runs": "739",
            "Soft": "6.0.9",
            "Setup": "30.06.2021",
            "PM": "05.2022",
            "Year": "2010",
            "Tech": "Ciobanu"
        },
        {
            "No": "10",
            "Client": "Buzau 2",
            "Serial": "1T05509",
            "Hours": "1699",
            "Runs": "492",
            "Soft": "6.0.9",
            "Setup": "27.09.2021",
            "PM": "11.2022",
            "Year": "2011",
            "Tech": "Cristea"
        },
        {
            "No": "11",
            "Client": "Iasi 2",
            "Serial": "1T05545",
            "Hours": "919",
            "Runs": "363",
            "Soft": "6.0.8",
            "Setup": "16.11.2020",
            "PM": "12.2022",
            "Year": "2012",
            "Tech": "Cristea"
        },
        {
            "No": "12",
            "Client": "Depozit 2",
            "Serial": "1T05945",
            "Hours": "14109",
            "Runs": "4048",
            "Soft": "6.0.8",
            "Setup": "-",
            "PM": "03.2023",
            "Year": "2013",
            "Tech": "Ciobanu"
        },
        {
            "No": "13",
            "Client": "Alba",
            "Serial": "1T06293",
            "Hours": "4787",
            "Runs": "2416",
            "Soft": "6.0.6",
            "Setup": "18.11.2020",
            "PM": "12.2022",
            "Year": "2013",
            "Tech": "Ciobanu"
        },
        {
            "No": "14",
            "Client": "Ploiesti",
            "Serial": "1T06304",
            "Hours": "5516",
            "Runs": "2602",
            "Soft": "6.0.6",
            "Setup": "19.08.2020",
            "PM": "11.2022",
            "Year": "2013",
            "Tech": "Cristea"
        },
        {
            "No": "15",
            "Client": "Arad",
            "Serial": "1T06368",
            "Hours": "2277",
            "Runs": "999",
            "Soft": "6.0.6",
            "Setup": "23.07.2019",
            "PM": "11.2022",
            "Year": "2013",
            "Tech": "Ciobanu"
        },
        {
            "No": "16",
            "Client": "Tg. Mures",
            "Serial": "1T06369",
            "Hours": "995",
            "Runs": "549",
            "Soft": "6.0.6",
            "Setup": "15.07.2019",
            "PM": "12.2022",
            "Year": "2013",
            "Tech": "Cristea"
        },
        {
            "No": "17",
            "Client": "Iasi 1",
            "Serial": "1T06370",
            "Hours": "2006",
            "Runs": "1010",
            "Soft": "6.0.6",
            "Setup": "19.07.2019",
            "PM": "12.2022",
            "Year": "2013",
            "Tech": "Cristea"
        },
        {
            "No": "18",
            "Client": "Galati",
            "Serial": "1T06387",
            "Hours": "1954",
            "Runs": "1231",
            "Soft": "6.0.6",
            "Setup": "09.08.2019",
            "PM": "11.2022",
            "Year": "2013",
            "Tech": "Cristea"
        },
        {
            "No": "19",
            "Client": "Satu Mare 1",
            "Serial": "1T06388",
            "Hours": "937",
            "Runs": "774",
            "Soft": "6.0.6",
            "Setup": "16.07.2019",
            "PM": "12.2022",
            "Year": "2013",
            "Tech": "Ciobanu"
        },
        {
            "No": "20",
            "Client": "Craiova",
            "Serial": "1T06861",
            "Hours": "1272",
            "Runs": "698",
            "Soft": "6.0.6",
            "Setup": "16.11.2020",
            "PM": "12.2022",
            "Year": "2014",
            "Tech": "Cristea"
        },
        {
            "No": "21",
            "Client": "Zalau",
            "Serial": "1T06940",
            "Hours": "1990",
            "Runs": "1256",
            "Soft": "6.0.6",
            "Setup": "07.08.2019",
            "PM": "11.2022",
            "Year": "2015",
            "Tech": "Ciobanu"
        },
        {
            "No": "22",
            "Client": "Timisoara 1",
            "Serial": "1T06941",
            "Hours": "2662",
            "Runs": "1122",
            "Soft": "6.0.6",
            "Setup": "23.07.2019",
            "PM": "11.2022",
            "Year": "2015",
            "Tech": "Ciobanu"
        },
        {
            "No": "23",
            "Client": "Bucuresti",
            "Serial": "1T07368",
            "Hours": "3119",
            "Runs": "973",
            "Soft": "6.0.9",
            "Setup": "06.07.2022",
            "PM": "01.2023",
            "Year": "2016",
            "Tech": "Ciobanu"
        },
        {
            "No": "24",
            "Client": "Cluj 1",
            "Serial": "1T07449",
            "Hours": "3872",
            "Runs": "1267",
            "Soft": "6.0.9",
            "Setup": "18.11.2020",
            "PM": "12.2022",
            "Year": "2016",
            "Tech": "Ciobanu"
        },
        {
            "No": "25",
            "Client": "Oradea 1",
            "Serial": "1T07660",
            "Hours": "1527",
            "Runs": "919",
            "Soft": "6.0.6",
            "Setup": "12.03.2020",
            "PM": "11.2022",
            "Year": "2016",
            "Tech": "Ciobanu"
        },
        {
            "No": "26",
            "Client": "Bucuresti",
            "Serial": "1T08023",
            "Hours": "1443",
            "Runs": "856",
            "Soft": "6.0.6",
            "Setup": "21.10.2019",
            "PM": "11.2022",
            "Year": "2016",
            "Tech": "Ciobanu"
        },
        {
            "No": "27",
            "Client": "Oradea 2",
            "Serial": "1T09702",
            "Hours": "1977",
            "Runs": "1332",
            "Soft": "6.0.8",
            "Setup": "11.12.2019",
            "PM": "11.2022",
            "Year": "2019",
            "Tech": "Ciobanu"
        },
        {
            "No": "28",
            "Client": "Timisoara 2",
            "Serial": "1T11170",
            "Hours": "1538",
            "Runs": "654",
            "Soft": "6.0.9",
            "Setup": "25.02.2021",
            "PM": "11.2022",
            "Year": "2020",
            "Tech": "Ciobanu"
        },
        {
            "No": "29",
            "Client": "Pitesti 2",
            "Serial": "1T11206",
            "Hours": "312",
            "Runs": "266",
            "Soft": "6.0.9",
            "Setup": "19.04.2021",
            "PM": "12.2022",
            "Year": "2021",
            "Tech": "Cristea"
        },
        {
            "No": "30",
            "Client": "Sibiu",
            "Serial": "1T11341",
            "Hours": "145",
            "Runs": "102",
            "Soft": "6.0.9",
            "Setup": "08.06.2021",
            "PM": "12.2022",
            "Year": "2021",
            "Tech": "Ciobanu"
        },
        {
            "No": "31",
            "Client": "Pitesti 1",
            "Serial": "1T11932",
            "Hours": "66",
            "Runs": "48",
            "Soft": "6.0.9",
            "Setup": "05.04.2022",
            "PM": "12.2022",
            "Year": "2021",
            "Tech": "Cristea"
        },
        {
            "No": "32",
            "Client": "Depozit 3",
            "Serial": "1T12300",
            "Hours": "-",
            "Runs": "-",
            "Soft": "6.0.9",
            "Setup": "-",
            "PM": "12.2022",
            "Year": "2021",
            "Tech": "Cristea"
        }
    ]
}